rate_limiter/__init__.py
rate_limiter/limiter.py
meow_redis_ratelimiter-0.1.0.dist-info/METADATA
meow_redis_ratelimiter-0.1.0.dist-info/WHEEL
meow_redis_ratelimiter-0.1.0.dist-info/top_level.txt
meow_redis_ratelimiter-0.1.0.dist-info/RECORD
