Metadata-Version: 2.4
Name: meow-redis-ratelimiter
Version: 0.1.0
Summary: A framework-agnostic rate limiter for Python backends (Flask, Django, FastAPI, etc.)
Home-page: https://github.com/shashaaankkkkk/meow-redis-ratelimiter
Author: Shashank Shekhar
Author-email: Shashank Shekhar <shashankshekhar8534@gmail.com>
License: MIT
Project-URL: Homepage, https://github.com/shashaaankkkkk/meow-redis-ratelimiter
Requires-Python: >=3.7
Requires-Dist: redis>=5.0.0
